simpleTokenStore/__init__.py
simpleTokenStore/simpleTokenStore.py
simpletokenstore-1.0.dist-info/licenses/LICENSE
simpletokenstore-1.0.dist-info/METADATA
simpletokenstore-1.0.dist-info/WHEEL
simpletokenstore-1.0.dist-info/top_level.txt
simpletokenstore-1.0.dist-info/RECORD
