Metadata-Version: 2.4
Name: simpleTokenStore
Version: 1.0
Summary: token storage made simple
Author-email: Phillip Harry T <philliptinsley44@gmail.com>
License: Apache NON-AI License, Version 2.0
Keywords: token,webtoken,api,key,local storage,json,JSON,query,session,jwt,JWT
Classifier: License :: Other/Proprietary License
Classifier: Programming Language :: Python
Classifier: Programming Language :: Python :: 3
Classifier: Intended Audience :: Information Technology
Requires-Python: >=3.8
License-File: LICENSE
Dynamic: license-file
